logsight/__init__.py
logsight/applications.py
logsight/config.py
logsight/exceptions.py
logsight/incidents.py
logsight/logger.py
logsight/quality.py
logsight/result.py
logsight/template.py
logsight/utils.py
logsight_sdk_py-0.0.19.dist-info/LICENSE
logsight_sdk_py-0.0.19.dist-info/METADATA
logsight_sdk_py-0.0.19.dist-info/WHEEL
logsight_sdk_py-0.0.19.dist-info/top_level.txt
logsight_sdk_py-0.0.19.dist-info/RECORD
