Metadata-Version: 2.1
Name: logsight-sdk-py
Version: 0.0.19
Summary: Logsight SDK Python
Home-page: https://github.com/aiops/logsight-sdk-py
Author: Jorge Cardoso
Author-email: jorge.cardoso.pt@gmail.com
License: unlicense
Project-URL: Documentation, http://logsight.readthedocs.io/en/latest/
Project-URL: Source, https://github.com/aiops/logsight-sdk-py
Project-URL: Tracker, https://github.com/aiops/logsight-sdk-py/issues
Platform: UNKNOWN
Classifier: Development Status :: 3 - Alpha
Classifier: Programming Language :: Python :: 3.6
Classifier: Programming Language :: Python :: 3.7
Classifier: Programming Language :: Python :: 3.8
Classifier: Programming Language :: Python :: 3.9
Classifier: Operating System :: OS Independent
Classifier: Topic :: Utilities
Requires-Python: >=3.6
License-File: LICENSE
Requires-Dist: requests
